azcrawlerpy/__init__.py
azcrawlerpy/crawling/__init__.py
azcrawlerpy/crawling/actions.py
azcrawlerpy/crawling/browser_utils.py
azcrawlerpy/crawling/config.py
azcrawlerpy/crawling/crawler.py
azcrawlerpy/crawling/data_extraction.py
azcrawlerpy/crawling/diagnostics.py
azcrawlerpy/crawling/discovery.py
azcrawlerpy/crawling/discovery_models.py
azcrawlerpy/crawling/exceptions.py
azcrawlerpy/crawling/field_handlers.py
azcrawlerpy/crawling/models.py
azcrawlerpy/crawling/utils.py
azcrawlerpy/handling/__init__.py
azcrawlerpy/handling/base.py
azcrawlerpy/handling/validation.py
azcrawlerpy/validation/__init__.py
azcrawlerpy/validation/base.py
azcrawlerpy/validation/config.py
azcrawlerpy/validation/crawl.py
azcrawlerpy/validation/crawler.py
azcrawlerpy/validation/data.py
azcrawlerpy/validation/proxy.py
azcrawlerpy/validation/request.py
azcrawlerpy/validation/run.py
azcrawlerpy-0.3.3.dist-info/METADATA
azcrawlerpy-0.3.3.dist-info/WHEEL
azcrawlerpy-0.3.3.dist-info/top_level.txt
azcrawlerpy-0.3.3.dist-info/RECORD
