Metadata-Version: 2.4
Name: azcrawlerpy
Version: 0.3.3
Summary: Agentic Crawler Discovery Framework.
Classifier: Programming Language :: Python :: 3
Classifier: Operating System :: OS Independent
Requires-Python: <3.12,>=3.11.10
Requires-Dist: playwright==1.48.0
Requires-Dist: pydantic>=2.11.10
Requires-Dist: camoufox[geoip]>=0.4.0
Provides-Extra: dev
Requires-Dist: pytest==8.4.2; extra == "dev"
Requires-Dist: pytest-asyncio==1.0.0; extra == "dev"
Requires-Dist: pytest-mock==3.14.1; extra == "dev"
Requires-Dist: pytest-cov>=4.1.0; extra == "dev"
Requires-Dist: pyright>=1.1.390; extra == "dev"
Requires-Dist: ruff>=0.8.0; extra == "dev"
